david8/__init__.py
david8/cast_types.py
david8/expressions.py
david8/functions.py
david8/joins.py
david8/logical_operators.py
david8/param_styles.py
david8/predicates.py
david8/core/__init__.py
david8/core/arg_convertors.py
david8/core/base_aliased.py
david8/core/base_ddl.py
david8/core/base_dialect.py
david8/core/base_dml.py
david8/core/base_dql.py
david8/core/base_expressions.py
david8/core/base_params.py
david8/core/base_query.py
david8/core/base_query_builder.py
david8/core/fn_generator.py
david8/core/log.py
david8/core/sql_92_join.py
david8/protocols/__init__.py
david8/protocols/dialect.py
david8/protocols/query_builder.py
david8/protocols/sql.py
david8-1.0.0b1.dist-info/licenses/LICENSE
david8-1.0.0b1.dist-info/METADATA
david8-1.0.0b1.dist-info/WHEEL
david8-1.0.0b1.dist-info/top_level.txt
david8-1.0.0b1.dist-info/RECORD
